odoo/addons/product_supplierinfo_revision/README.rst
odoo/addons/product_supplierinfo_revision/__init__.py
odoo/addons/product_supplierinfo_revision/__manifest__.py
odoo/addons/product_supplierinfo_revision/i18n/ca.po
odoo/addons/product_supplierinfo_revision/i18n/es.po
odoo/addons/product_supplierinfo_revision/i18n/fr.po
odoo/addons/product_supplierinfo_revision/i18n/it.po
odoo/addons/product_supplierinfo_revision/i18n/product_supplierinfo_revision.pot
odoo/addons/product_supplierinfo_revision/models/__init__.py
odoo/addons/product_supplierinfo_revision/models/product_supplierinfo.py
odoo/addons/product_supplierinfo_revision/readme/CONTRIBUTORS.md
odoo/addons/product_supplierinfo_revision/readme/DESCRIPTION.md
odoo/addons/product_supplierinfo_revision/readme/USAGE.md
odoo/addons/product_supplierinfo_revision/security/ir.model.access.csv
odoo/addons/product_supplierinfo_revision/static/description/icon.png
odoo/addons/product_supplierinfo_revision/static/description/index.html
odoo/addons/product_supplierinfo_revision/tests/__init__.py
odoo/addons/product_supplierinfo_revision/tests/test_product_supplierinfo_revision.py
odoo/addons/product_supplierinfo_revision/views/product_supplierinfo_view.xml
odoo/addons/product_supplierinfo_revision/wizards/__init__.py
odoo/addons/product_supplierinfo_revision/wizards/supplierinfo_duplicate_wizard.py
odoo/addons/product_supplierinfo_revision/wizards/supplierinfo_duplicate_wizard_view.xml
odoo_addon_product_supplierinfo_revision-18.0.1.0.0.5.dist-info/METADATA
odoo_addon_product_supplierinfo_revision-18.0.1.0.0.5.dist-info/WHEEL
odoo_addon_product_supplierinfo_revision-18.0.1.0.0.5.dist-info/top_level.txt
odoo_addon_product_supplierinfo_revision-18.0.1.0.0.5.dist-info/RECORD
